mysql_lingling/__init__.py
mysql_lingling-0.0.8.dist-info/LICENSE
mysql_lingling-0.0.8.dist-info/METADATA
mysql_lingling-0.0.8.dist-info/WHEEL
mysql_lingling-0.0.8.dist-info/top_level.txt
mysql_lingling-0.0.8.dist-info/RECORD
