Metadata-Version: 2.1
Name: mysql-lingling
Version: 0.0.8
Summary: 对 mysql-connector 的二次封装
Home-page: https://github.com/qq20004604/my-pip-package-list/tree/master/mysql_lingling/packaging_tutorial
Author: Wang Dong
Author-email: 20004604@qq.com
License: UNKNOWN
Platform: UNKNOWN
Classifier: Programming Language :: Python :: 3
Classifier: License :: OSI Approved :: MIT License
Classifier: Operating System :: OS Independent
Requires-Dist: mysql-connector (>=2.2.9)
